gabiking_pygame_widgets/__init__.py
gabiking_pygame_widgets/widgets.py
gabiking_pygame_widgets-1.0.2.dist-info/LICENSE
gabiking_pygame_widgets-1.0.2.dist-info/METADATA
gabiking_pygame_widgets-1.0.2.dist-info/WHEEL
gabiking_pygame_widgets-1.0.2.dist-info/top_level.txt
gabiking_pygame_widgets-1.0.2.dist-info/RECORD
