Metadata-Version: 2.2
Name: gabiking-pygame-widgets
Version: 1.0.2
Summary: This package provides widgets for a more friendly interface with PyGame.
Author: Gabriel
License: MIT
Classifier: Programming Language :: Python :: 3
Classifier: License :: OSI Approved :: MIT License
Classifier: Operating System :: OS Independent
License-File: LICENSE
Requires-Dist: pygame
